<?xml version="1.0"?>
<window type="dialog" id="11000">
		<defaultcontrol always="true">52</defaultcontrol>
		<allowoverlay>no</allowoverlay>
		<controls>
            <control type="image" id="9110">
				<posy>0</posy>
				<posx>0</posx>
				<width>1920</width>
				<height>1080</height>
				<align>center</align>
				<aligny>center</aligny>
				<texture flipY="true" flipX="false">background.jpg</texture>
			</control>
            <control type="label" id="9111">
				<posy>-300</posy>
				<posx>0</posx>
				<font>font20</font>
				<label>Для активации устройства посетите</label>
				<wrapmultiline>true</wrapmultiline>
				<textcolor>white</textcolor>
				<selectedcolor>white</selectedcolor>
				<align>center</align>
				<aligny>center</aligny>
			</control>
            <control type="label" id="9112">
				<posy>-200</posy>
				<posx>0</posx>
				<font>font30</font>
				<label>-</label>
				<wrapmultiline>true</wrapmultiline>
				<textcolor>ffbcd5ff</textcolor>
				<selectedcolor>ffbcd5ff</selectedcolor>
				<align>center</align>
				<aligny>center</aligny>
			</control>
			<control type="label" id="9113">
				<posy>0</posy>
				<posx>0</posx>
				<font>font35_title</font>
				<label>-</label>
				<wrapmultiline>true</wrapmultiline>
				<textcolor>white</textcolor>
				<selectedcolor>white</selectedcolor>
				<align>center</align>
				<aligny>center</aligny>
			</control>
		</controls>
</window>

